{
  "version": 1,
  "lastVerified": "2026-04-13",
  "notes": "Curated seed of certified-green hostels. Every non-placeholder entry has been cross-checked against a publicly cited source (hostel operator page or certification-body news item). Entries flagged with verify=true are placeholders for cities where a specific hostel's certification could not be confirmed from the cert body's public directory at seed time and must be validated (or removed) before launch. Refresh quarterly.",
  "hostels": [
    {
      "id": "mije-fauconnier-paris",
      "cityId": "par",
      "countryId": "FR",
      "name": "MIJE Fauconnier",
      "cert": "Green Key",
      "certLevel": null,
      "url": "https://www.mije.com/en/youth-hostel-in-paris/fauconnier",
      "lat": 48.854,
      "lng": 2.3576,
      "priceTier": "mid",
      "sustainabilityScore": 4,
      "verifiedAt": "2026-04-13",
      "sourceUrl": "https://www.mije.com/en/youth-hostel-in-paris/the-green-key-label-of-the-mije-fauconnier-hostel"
    },
    {
      "id": "hi-paris-yves-robert",
      "cityId": "par",
      "countryId": "FR",
      "name": "Auberge de Jeunesse HI Paris - Yves Robert",
      "cert": "Green Key",
      "certLevel": null,
      "url": "https://www.hifrance.org/en/youth-hostels/paris-yves-robert/",
      "lat": 48.8888,
      "lng": 2.3628,
      "priceTier": "mid",
      "sustainabilityScore": 4,
      "verifiedAt": "2026-04-13",
      "sourceUrl": "https://www.hifrance.org/en/about-us/the-labels/green-key/"
    },
    {
      "id": "sleep-green-barcelona",
      "cityId": "bcn",
      "countryId": "ES",
      "name": "Sleep Green - Certified Eco Youth Hostel Barcelona",
      "cert": "EU Ecolabel",
      "certLevel": null,
      "url": "https://sleepgreenbarcelona.com/",
      "lat": 41.3863,
      "lng": 2.1687,
      "priceTier": "mid",
      "sustainabilityScore": 4,
      "verifiedAt": "2026-04-13",
      "sourceUrl": "https://sleepgreenbarcelona.com/"
    },
    {
      "id": "kabul-barcelona",
      "cityId": "bcn",
      "countryId": "ES",
      "name": "Kabul Party Hostel Barcelona",
      "cert": "Biosphere",
      "certLevel": null,
      "url": "https://www.kabul.es/",
      "lat": 41.3798,
      "lng": 2.1749,
      "priceTier": "low",
      "sustainabilityScore": 4,
      "verifiedAt": "2026-04-13",
      "sourceUrl": "https://www.kabul.es/2025-biosphere-certification-of-sustainability/"
    },
    {
      "id": "steel-house-copenhagen",
      "cityId": "cph",
      "countryId": "DK",
      "name": "Steel House Copenhagen",
      "cert": "Green Key",
      "certLevel": null,
      "url": "https://www.steelhousecopenhagen.com/",
      "lat": 55.6779,
      "lng": 12.5663,
      "priceTier": "mid",
      "sustainabilityScore": 4,
      "verifiedAt": "2026-04-13",
      "sourceUrl": "https://www.greenkey.dk/en/map-details/steel-house-copenhagen"
    },
    {
      "id": "stf-skeppsholmen-stockholm",
      "cityId": "sto",
      "countryId": "SE",
      "name": "STF af Chapman & Skeppsholmen Hostel",
      "cert": "Green Key",
      "certLevel": null,
      "url": "https://www.swedishtouristassociation.com/facilities/stf-stockholm-skeppsholmen-hostel/",
      "lat": 59.3247,
      "lng": 18.0805,
      "priceTier": "mid",
      "sustainabilityScore": 4,
      "verifiedAt": "2026-04-13",
      "sourceUrl": "https://destinet.eu/who-who/market-place/certifiers-section/international-green-key/stf-af-chapman-skeppsholmen-hostel"
    },
    {
      "id": "placeholder-berlin-01",
      "cityId": "ber",
      "countryId": "DE",
      "name": "[VERIFY] Berlin Green Key hostel",
      "cert": "Green Key",
      "certLevel": null,
      "url": null,
      "lat": null,
      "lng": null,
      "priceTier": "mid",
      "sustainabilityScore": 4,
      "verifiedAt": null,
      "sourceUrl": "https://www.greenkey.global/green-key-sites",
      "verify": true,
      "verifyNote": "Berlin operators often use GreenSign (a&o Hostels) rather than Green Key; Green Key directory must be cross-checked interactively before shipping a specific Berlin entry."
    },
    {
      "id": "placeholder-amsterdam-01",
      "cityId": "ams",
      "countryId": "NL",
      "name": "[VERIFY] ClinkMama Amsterdam (formerly Ecomama)",
      "cert": "Green Key",
      "certLevel": null,
      "url": "https://www.clinkhostels.com/clinkmama/",
      "lat": 52.3683,
      "lng": 4.9108,
      "priceTier": "mid",
      "sustainabilityScore": 4,
      "verifiedAt": null,
      "sourceUrl": "https://www.greenkey.global/green-key-sites",
      "verify": true,
      "verifyNote": "Third-party sustainability write-ups claim Green Key + Eco-Dynamic certification; not yet cross-referenced against the Green Key Netherlands directory page."
    },
    {
      "id": "placeholder-madrid-01",
      "cityId": "mad",
      "countryId": "ES",
      "name": "[VERIFY] Madrid certified-green hostel",
      "cert": "EU Ecolabel",
      "certLevel": null,
      "url": null,
      "lat": null,
      "lng": null,
      "priceTier": "mid",
      "sustainabilityScore": 4,
      "verifiedAt": null,
      "sourceUrl": "https://environment.ec.europa.eu/topics/circular-economy/eu-ecolabel_en",
      "verify": true,
      "verifyNote": "No Madrid hostel could be confirmed in the EU Ecolabel tourist-accommodation registry during seed research; curator must consult the Ecolabel product-group database directly."
    },
    {
      "id": "placeholder-vienna-01",
      "cityId": "vie",
      "countryId": "AT",
      "name": "[VERIFY] Vienna certified-green hostel",
      "cert": "EU Ecolabel",
      "certLevel": null,
      "url": null,
      "lat": null,
      "lng": null,
      "priceTier": "mid",
      "sustainabilityScore": 4,
      "verifiedAt": null,
      "sourceUrl": "https://environment.ec.europa.eu/topics/circular-economy/eu-ecolabel_en",
      "verify": true,
      "verifyNote": "Austria runs a strong Österreichisches Umweltzeichen programme in parallel to EU Ecolabel; curator should consult umweltzeichen.at for hostel entries before assigning a cert."
    },
    {
      "id": "placeholder-prague-01",
      "cityId": "prg",
      "countryId": "CZ",
      "name": "[VERIFY] Prague certified-green hostel",
      "cert": "Green Key",
      "certLevel": null,
      "url": null,
      "lat": null,
      "lng": null,
      "priceTier": "mid",
      "sustainabilityScore": 4,
      "verifiedAt": null,
      "sourceUrl": "https://www.greenkey.global/green-key-sites",
      "verify": true,
      "verifyNote": "Mosaic House Design Hotel holds BREEAM In-Use Excellent (not in our accepted enum). No Green Key hostel was confirmed in Prague during seed research."
    },
    {
      "id": "placeholder-lisbon-01",
      "cityId": "lis",
      "countryId": "PT",
      "name": "[VERIFY] Lisbon certified-green hostel",
      "cert": "Green Key",
      "certLevel": null,
      "url": null,
      "lat": null,
      "lng": null,
      "priceTier": "mid",
      "sustainabilityScore": 4,
      "verifiedAt": null,
      "sourceUrl": "https://www.greenkey.global/green-key-sites",
      "verify": true,
      "verifyNote": "Green Key Portugal (ABAE) lists several Lisbon hotels (e.g. NEYA Lisboa) but no confirmed hostel at seed time. Curator must consult abae.pt / Green Key Portugal directory."
    }
  ]
}
